test_pdm-0.1.1.dist-info/METADATA
test_pdm-0.1.1.dist-info/WHEEL
test_pdm/__init__.py
test_pdm/test.py
test_pdm-0.1.1.dist-info/RECORD
