Metadata-Version: 2.1
Name: test-pdm
Version: 0.1.1
Summary: test repository add-on
Keywords: pdm-test test
Author-Email: Jrxvx <Dxsx1226dev@gmail.com>
License: MIT
Classifier: Topic :: Software Development :: Build Tools
Classifier: Programming Language :: Python :: 3
Classifier: Programming Language :: Python :: 3.8
Classifier: Programming Language :: Python :: 3.9
Classifier: Programming Language :: Python :: 3.10
Classifier: Programming Language :: Python :: 3.11
Classifier: Programming Language :: Python :: 3.12
Project-URL: Homepage, https://github.com/Jrxvx
Project-URL: Repository, https://github.com/Jrxvx/fast-flet
Project-URL: Documentation, https://github.com/Jrxvx/fast-flet
Project-URL: Changelog, https://pdm-project.org/latest/dev/changelog/
Requires-Python: >=3.8
Requires-Dist: parse>=1.20.0
